sqlparser/__init__.py
sqlparser/internalparser.py
sqlparser/parsing.py
sqlparser/stringparser.py
sqlparser/utils.py
sqlparser/generated/SqlBaseLexer.py
sqlparser/generated/SqlBaseListener.py
sqlparser/generated/SqlBaseParser.py
sqlparser/grammar/SqlBase.g4
pythonsqlparser-0.1.2.dist-info/LICENSE
pythonsqlparser-0.1.2.dist-info/METADATA
pythonsqlparser-0.1.2.dist-info/WHEEL
pythonsqlparser-0.1.2.dist-info/top_level.txt
pythonsqlparser-0.1.2.dist-info/RECORD
