Metadata-Version: 2.1
Name: pythonsqlparser
Version: 0.1.2
Summary: This repository provides a Python SQL string parser.
Home-page: https://github.com/pysparkling/python-sql-parser/
Author: Erwan Guyomarc'h
Author-email: tools4origins@gmail.com
License: Apache-2.0
Platform: UNKNOWN
Classifier: Development Status :: 4 - Beta
Classifier: Intended Audience :: Developers
Classifier: License :: OSI Approved :: Apache Software License
Classifier: Natural Language :: English
Classifier: Operating System :: OS Independent
Classifier: Programming Language :: Python
Classifier: Programming Language :: Python :: 3
Classifier: Programming Language :: Python :: 3 :: Only
Classifier: Programming Language :: Python :: 3.4
Classifier: Programming Language :: Python :: 3.5
Classifier: Programming Language :: Python :: 3.6
Classifier: Programming Language :: Python :: 3.7
Classifier: Programming Language :: Python :: 3.8
Classifier: Programming Language :: Python :: 3.9
Classifier: Programming Language :: Python :: Implementation :: CPython
Classifier: Programming Language :: Python :: Implementation :: PyPy
Requires-Python: >=3.4
Requires-Dist: antlr4-python3-runtime (==4.7.1)
Provides-Extra: test
Requires-Dist: pylint (~=2.5.0) ; extra == 'test'
Requires-Dist: pytest ; extra == 'test'
